Metadata-Version: 2.1
Name: django-ndarrayfield
Version: 1.0.0rc4
Summary: Yet another numpy ndarray fields for Django
Home-page: https://github.com/ORTHOIN3D/django-ndarrayfield
Author: Aurélien Moreau
Author-email: aurelien.moreau@yienyien.net
License: UNKNOWN
Platform: UNKNOWN
Requires-Python: >=3.6
